odoo/addons/hr_contract_employee_calendar_planning/README.rst
odoo/addons/hr_contract_employee_calendar_planning/__init__.py
odoo/addons/hr_contract_employee_calendar_planning/__manifest__.py
odoo/addons/hr_contract_employee_calendar_planning/hooks.py
odoo/addons/hr_contract_employee_calendar_planning/i18n/hr_contract_employee_calendar_planning.pot
odoo/addons/hr_contract_employee_calendar_planning/i18n/it.po
odoo/addons/hr_contract_employee_calendar_planning/models/__init__.py
odoo/addons/hr_contract_employee_calendar_planning/models/contract.py
odoo/addons/hr_contract_employee_calendar_planning/readme/CONTRIBUTORS.md
odoo/addons/hr_contract_employee_calendar_planning/readme/DESCRIPTION.md
odoo/addons/hr_contract_employee_calendar_planning/readme/USAGE.md
odoo/addons/hr_contract_employee_calendar_planning/static/description/icon.png
odoo/addons/hr_contract_employee_calendar_planning/static/description/index.html
odoo/addons/hr_contract_employee_calendar_planning/tests/__init__.py
odoo/addons/hr_contract_employee_calendar_planning/tests/test_hr_contract_employee_calendar_planning.py
odoo/addons/hr_contract_employee_calendar_planning/views/contract.xml
odoo_addon_hr_contract_employee_calendar_planning-18.0.1.0.0.2.dist-info/METADATA
odoo_addon_hr_contract_employee_calendar_planning-18.0.1.0.0.2.dist-info/WHEEL
odoo_addon_hr_contract_employee_calendar_planning-18.0.1.0.0.2.dist-info/top_level.txt
odoo_addon_hr_contract_employee_calendar_planning-18.0.1.0.0.2.dist-info/RECORD
